{
    "id": "callback_onuserenablevideo",
    "name": "userEnableVideo",
    "description": "Occurs when a remote user enables/disables the video module.\nOnce the video module is disabled, the user can only use a voice call. The user cannot send or receive any video.\n   The SDK triggers this callback when a remote user enables or disables the video module by calling the enableVideo or disableVideo method.",
    "parameters": [
        {
            "uid": "The user ID of the remote user."
        },
        {
            "enabled": "\n                        \n                            true: Enable.\n                            false: Disable.\n                        \n                    "
        }
    ],
    "returns": ""
}
