{
    "id": "callback_ichanneleventhandler_onremotevideostatechanged",
    "name": "remoteVideoStateChanged",
    "description": "Occurs when the remote video state changes.\nThis callback does not work properly when the number of users (in the voice/video call channel) or hosts (in the live streaming channel) in the channel exceeds 17.",
    "parameters": [
        {
            "reason": " The reason for the remote video state\n                              change, see VideoRemoteStateReason. "
        },
        {
            "state": " The state of the remote video, see\n                              VideoRemoteState. "
        },
        {
            "uid": ""
        },
        {
            "elapsed": "Time elapsed (ms) from the local user calling the joinChannel method until the SDK triggers this callback."
        }
    ],
    "returns": ""
}
